netController/__init__.py
netController/nas_inventory.py
netController/ssh_sbi.py
netController-0.0.16.dist-info/METADATA
netController-0.0.16.dist-info/WHEEL
netController-0.0.16.dist-info/top_level.txt
netController-0.0.16.dist-info/RECORD
