Metadata-Version: 2.1
Name: netController
Version: 0.0.16
Summary: NAS-Network-Controller
Author: Emiliano Rosico
Author-email: <emiliano19@gmail.com>
Keywords: python,networController,MAT,IQUALL
Classifier: Development Status :: 3 - Alpha
Classifier: Intended Audience :: Education
Classifier: Programming Language :: Python :: 2
Classifier: Programming Language :: Python :: 3
Classifier: Operating System :: MacOS :: MacOS X
Classifier: Operating System :: Microsoft :: Windows
Requires-Dist: netmiko ==2.4.2
Requires-Dist: Cryptography ==36.0.1
